rtrec/__init__.py
rtrec/recommender.py
rtrec/experiments/datasets.py
rtrec/experiments/experiments.py
rtrec/experiments/kaggle_datasets.py
rtrec/experiments/split.py
rtrec/experiments/utils.py
rtrec/models/__init__.py
rtrec/models/base.py
rtrec/models/hybrid.py
rtrec/models/lightfm.py
rtrec/models/slim.py
rtrec/models/internal/lightfm_wrapper.py
rtrec/models/internal/slim_elastic.py
rtrec/serving/app.py
rtrec/utils/collections.py
rtrec/utils/diskcache.py
rtrec/utils/features.py
rtrec/utils/identifiers.py
rtrec/utils/interactions.py
rtrec/utils/lang.py
rtrec/utils/lru.py
rtrec/utils/math.py
rtrec/utils/metrics.py
rtrec/utils/multiprocessing.py
rtrec/utils/pandas.py
rtrec/utils/scoring.py
rtrec-0.2.7.dist-info/METADATA
rtrec-0.2.7.dist-info/WHEEL
rtrec-0.2.7.dist-info/licenses/LICENSE
rtrec-0.2.7.dist-info/RECORD
