Metadata-Version: 2.4
Name: rtrec
Version: 0.2.7
Summary: A realtime recommendation system supporting online updates
Project-URL: homepage, https://github.com/myui/rtrec
Project-URL: repository, https://github.com/myui/rtrec
Author-email: myui <myui@apache.org>
License-File: LICENSE
Keywords: machine learning,personalization,recommendation systems,recommender,recsys
Classifier: Development Status :: 5 - Production/Stable
Classifier: Intended Audience :: Developers
Classifier: Intended Audience :: Science/Research
Classifier: License :: OSI Approved :: BSD License
Classifier: Operating System :: OS Independent
Classifier: Programming Language :: Python
Classifier: Programming Language :: Python :: 3
Classifier: Programming Language :: Python :: 3.10
Classifier: Programming Language :: Python :: 3.11
Classifier: Programming Language :: Python :: 3.12
Classifier: Programming Language :: Python :: 3.13
Classifier: Topic :: Scientific/Engineering :: Artificial Intelligence
Classifier: Topic :: Software Development :: Libraries :: Python Modules
Requires-Python: >=3.10
Requires-Dist: implicit<1.0.0,>=0.6.0
Requires-Dist: numpy<3.0.0,>=1.24.0
Requires-Dist: pandas<3.0.0,>=1.3.0
Requires-Dist: rectools-lightfm<2.0.0,>=1.17.3
Requires-Dist: scikit-learn<2.0.0,>=1.1.0
Requires-Dist: scipy<2.0.0,>=1.5.0
Requires-Dist: tqdm<5.0.0,>=4.60.0
Requires-Dist: typing-extensions<5.0.0,>=4.5.0
Provides-Extra: serving
Requires-Dist: fastapi<1.0.0,>=0.70.0; extra == 'serving'
Requires-Dist: httpx<1.0.0,>=0.20.0; extra == 'serving'
Requires-Dist: pydantic<3.0.0,>=1.10.0; extra == 'serving'
Requires-Dist: uvicorn<1.0.0,>=0.18.0; extra == 'serving'
